jacksung/__init__.py
jacksung/ai/GeoAttX.py
jacksung/ai/__init__.py
jacksung/ai/latex_tool.py
jacksung/ai/metrics.py
jacksung/ai/GeoNet/__init__.py
jacksung/ai/GeoNet/m_block.py
jacksung/ai/GeoNet/m_blockV2.py
jacksung/ai/GeoNet/m_network.py
jacksung/ai/GeoNet/m_networkV2.py
jacksung/ai/utils/__init__.py
jacksung/ai/utils/cmorph.py
jacksung/ai/utils/data_parallelV2.py
jacksung/ai/utils/fy.py
jacksung/ai/utils/goes.py
jacksung/ai/utils/gsmap.py
jacksung/ai/utils/imerg.py
jacksung/ai/utils/metsat.py
jacksung/ai/utils/norm_util.py
jacksung/ai/utils/util.py
jacksung/libs/times.ttf
jacksung/utils/__init__.py
jacksung/utils/base_db.py
jacksung/utils/cache.py
jacksung/utils/data_convert.py
jacksung/utils/exception.py
jacksung/utils/fastnumpy.py
jacksung/utils/figure.py
jacksung/utils/hash.py
jacksung/utils/image.py
jacksung/utils/log.py
jacksung/utils/login.py
jacksung/utils/mean_std.py
jacksung/utils/multi_task.py
jacksung/utils/number.py
jacksung/utils/nvidia.py
jacksung/utils/time.py
jacksung/utils/web.py
jacksung-0.0.4.50.dist-info/LICENSE
jacksung-0.0.4.50.dist-info/METADATA
jacksung-0.0.4.50.dist-info/WHEEL
jacksung-0.0.4.50.dist-info/entry_points.txt
jacksung-0.0.4.50.dist-info/top_level.txt
jacksung-0.0.4.50.dist-info/RECORD
